{"wave":1.5,"scoreCollected":0,"goldCollected":91,"towers":[],"enemies":[{"name":"Dog","horizontalPosition":1.03961635,"verticalPosition":-6.0},{"name":"Dog","horizontalPosition":-0.660584569,"verticalPosition":-6.0},{"name":"Orc","horizontalPosition":-7.36,"verticalPosition":-7.0784297},{"name":"Dog","horizontalPosition":-7.380638,"verticalPosition":-5.142894},{"name":"Dog","horizontalPosition":-6.05997849,"verticalPosition":-6.0},{"name":"Dog","horizontalPosition":-7.408145,"verticalPosition":-3.499657},{"name":"Orc","horizontalPosition":-7.36,"verticalPosition":-13.10146},{"name":"Dog","horizontalPosition":-7.500559,"verticalPosition":1.84970009},{"name":"Ogre","horizontalPosition":-7.50818,"verticalPosition":4.432997},{"name":"Orc","horizontalPosition":-7.394158,"verticalPosition":5.04626274}]}